azure/mgmt/applicationinsights/__init__.py
azure/mgmt/applicationinsights/_application_insights_management_client.py
azure/mgmt/applicationinsights/_configuration.py
azure/mgmt/applicationinsights/_serialization.py
azure/mgmt/applicationinsights/_version.py
azure/mgmt/applicationinsights/models.py
azure/mgmt/applicationinsights/py.typed
azure/mgmt/applicationinsights/aio/__init__.py
azure/mgmt/applicationinsights/aio/_application_insights_management_client.py
azure/mgmt/applicationinsights/aio/_configuration.py
azure/mgmt/applicationinsights/v2015_05_01/__init__.py
azure/mgmt/applicationinsights/v2015_05_01/_application_insights_management_client.py
azure/mgmt/applicationinsights/v2015_05_01/_configuration.py
azure/mgmt/applicationinsights/v2015_05_01/_patch.py
azure/mgmt/applicationinsights/v2015_05_01/_version.py
azure/mgmt/applicationinsights/v2015_05_01/py.typed
azure/mgmt/applicationinsights/v2015_05_01/aio/__init__.py
azure/mgmt/applicationinsights/v2015_05_01/aio/_application_insights_management_client.py
azure/mgmt/applicationinsights/v2015_05_01/aio/_configuration.py
azure/mgmt/applicationinsights/v2015_05_01/aio/_patch.py
azure/mgmt/applicationinsights/v2015_05_01/aio/operations/__init__.py
azure/mgmt/applicationinsights/v2015_05_01/aio/operations/_analytics_items_operations.py
azure/mgmt/applicationinsights/v2015_05_01/aio/operations/_annotations_operations.py
azure/mgmt/applicationinsights/v2015_05_01/aio/operations/_api_keys_operations.py
azure/mgmt/applicationinsights/v2015_05_01/aio/operations/_component_available_features_operations.py
azure/mgmt/applicationinsights/v2015_05_01/aio/operations/_component_current_billing_features_operations.py
azure/mgmt/applicationinsights/v2015_05_01/aio/operations/_component_feature_capabilities_operations.py
azure/mgmt/applicationinsights/v2015_05_01/aio/operations/_component_quota_status_operations.py
azure/mgmt/applicationinsights/v2015_05_01/aio/operations/_components_operations.py
azure_mgmt_applicationinsights-4.1.0.dist-info/LICENSE
azure_mgmt_applicationinsights-4.1.0.dist-info/METADATA
azure_mgmt_applicationinsights-4.1.0.dist-info/WHEEL
azure_mgmt_applicationinsights-4.1.0.dist-info/top_level.txt
azure_mgmt_applicationinsights-4.1.0.dist-info/RECORD
